<?xml version="1.0" encoding="UTF-8"?>
<!--This is the 153 Best matching
Use topkmatch.xsd to parse and validate the information (XMLSchema)--><BestMatch CandidateOntology="paragonsports-filastore" MatchIndex="153" MatchWeight="0.0" TargetOntology="www.filastore.com"><MatchedTerms Weight="0.0"><CandidateTerm>text: First Name: (firstname)</CandidateTerm><TargetTerm>text: *First Name (nm_first)</TargetTerm></MatchedTerms><MatchedTerms Weight="0.0"><CandidateTerm>text: Last Name: (lastname)</CandidateTerm><TargetTerm>text: *Last Name (nm_Last)</TargetTerm></MatchedTerms><MatchedTerms Weight="0.0"><CandidateTerm>text: Address 1: (address1)</CandidateTerm><TargetTerm>text: *Street Address (No street address? See note above.) (street)</TargetTerm></MatchedTerms><MatchedTerms Weight="0.0"><CandidateTerm>text: Address 2: (address2)</CandidateTerm><TargetTerm>text: *Street Address (No street address? See note above.) (line2)</TargetTerm></MatchedTerms><MatchedTerms Weight="0.0"><CandidateTerm>text: City: (city)</CandidateTerm><TargetTerm>text: *City (city)</TargetTerm></MatchedTerms><MatchedTerms Weight="0.0"><CandidateTerm>text: Zip Postal Number: (zip)</CandidateTerm><TargetTerm>text: *Zip Code (zip_dom)</TargetTerm></MatchedTerms><MatchedTerms Weight="0.0"><CandidateTerm>text: Phone: (phone)</CandidateTerm><TargetTerm>text: *Phone (phone_nbr)</TargetTerm></MatchedTerms><MatchedTerms Weight="0.0"><CandidateTerm>checkbox:  (same_address)</CandidateTerm><TargetTerm>checkbox: Check if billing and shipping addresses are the same. (chkDiffAddress)</TargetTerm></MatchedTerms><MatchedTerms Weight="0.0"><CandidateTerm>select: State: (state)</CandidateTerm><TargetTerm>select: *State Province (state_dom)</TargetTerm></MatchedTerms></BestMatch><!--For any questions regarding the Top K Framework please send to:ontobuilder@ie.technion.ac.il-->