<?xml version="1.0" encoding="UTF-8"?>
<!DOCTYPE ontology SYSTEM "dtds/ontology.dtd">
<ontology name="www.jobfinders.freeserve.co.uk" title="Jobfinders application form for cv" site="http://www.jobfinders.freeserve.co.uk/form2.htm">
    <classes>
        <class name="page">
            <domain type="" />
            <attributes />
            <axioms />
            <subclasses />
        </class>
        <class name="form">
            <domain type="" />
            <attributes>
                <attribute name="method" value="get">
                    <domain name="Choice" type="choice">
                        <entry>post</entry>
                        <entry>get</entry>
                    </domain>
                </attribute>
                <attribute name="action">
                    <domain name="URL" type="url" />
                </attribute>
            </attributes>
            <axioms />
            <subclasses />
        </class>
        <class name="input">
            <domain type="" />
            <attributes>
                <attribute name="name">
                    <domain name="Text" type="text" />
                </attribute>
                <attribute name="disabled" value="false">
                    <domain name="Boolean" type="boolean" />
                </attribute>
            </attributes>
            <axioms />
            <subclasses>
                <class name="text">
                    <domain type="" />
                    <attributes>
                        <attribute name="name">
                            <domain name="Text" type="text" />
                        </attribute>
                        <attribute name="disabled">
                            <domain name="Boolean" type="boolean" />
                        </attribute>
                        <attribute name="type" value="text">
                            <domain type="" />
                        </attribute>
                        <attribute name="defaultValue">
                            <domain name="Text" type="text" />
                        </attribute>
                        <attribute name="value">
                            <domain name="Text" type="text" />
                        </attribute>
                        <attribute name="size">
                            <domain name="Positive Integer" type="pinteger" />
                        </attribute>
                        <attribute name="maxLength">
                            <domain name="Positive Integer" type="pinteger" />
                        </attribute>
                        <attribute name="readOnly" value="false">
                            <domain name="Boolean" type="boolean" />
                        </attribute>
                    </attributes>
                    <axioms />
                    <subclasses />
                </class>
                <class name="password">
                    <domain type="" />
                    <attributes>
                        <attribute name="name">
                            <domain name="Text" type="text" />
                        </attribute>
                        <attribute name="disabled">
                            <domain name="Boolean" type="boolean" />
                        </attribute>
                        <attribute name="type" value="password">
                            <domain type="" />
                        </attribute>
                        <attribute name="defaultValue">
                            <domain name="Text" type="text" />
                        </attribute>
                        <attribute name="size">
                            <domain name="Positive Integer" type="text" />
                        </attribute>
                        <attribute name="maxLength">
                            <domain name="Positive Integer" type="pinteger" />
                        </attribute>
                        <attribute name="readOnly" value="false">
                            <domain name="Boolean" type="boolean" />
                        </attribute>
                    </attributes>
                    <axioms />
                    <subclasses />
                </class>
                <class name="file">
                    <domain type="" />
                    <attributes>
                        <attribute name="name">
                            <domain name="Text" type="text" />
                        </attribute>
                        <attribute name="disabled">
                            <domain name="Boolean" type="boolean" />
                        </attribute>
                        <attribute name="type" value="file">
                            <domain type="" />
                        </attribute>
                        <attribute name="size">
                            <domain name="Positive Integer" type="pinteger" />
                        </attribute>
                        <attribute name="maxLength">
                            <domain name="Positive Integer" type="pinteger" />
                        </attribute>
                        <attribute name="readOnly" value="false">
                            <domain name="Boolean" type="boolean" />
                        </attribute>
                    </attributes>
                    <axioms />
                    <subclasses />
                </class>
                <class name="hidden">
                    <domain type="" />
                    <attributes>
                        <attribute name="name">
                            <domain name="Text" type="text" />
                        </attribute>
                        <attribute name="disabled">
                            <domain name="Boolean" type="boolean" />
                        </attribute>
                        <attribute name="type" value="hidden">
                            <domain type="" />
                        </attribute>
                        <attribute name="type" value="button">
                            <domain type="" />
                        </attribute>
                    </attributes>
                    <axioms />
                    <subclasses />
                </class>
                <class name="checkbox">
                    <domain type="" />
                    <attributes>
                        <attribute name="name">
                            <domain name="Text" type="text" />
                        </attribute>
                        <attribute name="disabled">
                            <domain name="Boolean" type="boolean" />
                        </attribute>
                        <attribute name="type" value="checkbox">
                            <domain type="" />
                        </attribute>
                    </attributes>
                    <axioms />
                    <subclasses />
                </class>
                <class name="radio">
                    <domain type="" />
                    <attributes>
                        <attribute name="name">
                            <domain name="Text" type="text" />
                        </attribute>
                        <attribute name="disabled">
                            <domain name="Boolean" type="boolean" />
                        </attribute>
                        <attribute name="type" value="radio">
                            <domain type="" />
                        </attribute>
                    </attributes>
                    <axioms />
                    <subclasses />
                </class>
                <class name="select">
                    <domain type="" />
                    <attributes>
                        <attribute name="name">
                            <domain name="Text" type="text" />
                        </attribute>
                        <attribute name="disabled">
                            <domain name="Boolean" type="boolean" />
                        </attribute>
                        <attribute name="type" value="select">
                            <domain type="" />
                        </attribute>
                        <attribute name="size">
                            <domain name="Positive Integer" type="pinteger" />
                        </attribute>
                        <attribute name="multiple" value="false">
                            <domain name="Boolean" type="boolean" />
                        </attribute>
                    </attributes>
                    <axioms />
                    <subclasses />
                </class>
                <class name="textarea">
                    <domain type="" />
                    <attributes>
                        <attribute name="name">
                            <domain name="Text" type="text" />
                        </attribute>
                        <attribute name="disabled">
                            <domain name="Boolean" type="boolean" />
                        </attribute>
                        <attribute name="type" value="textarea">
                            <domain type="" />
                        </attribute>
                        <attribute name="defaultValue">
                            <domain name="Text" type="text" />
                        </attribute>
                        <attribute name="rows">
                            <domain name="Positive Integer" type="pinteger" />
                        </attribute>
                        <attribute name="cols">
                            <domain name="Positive Integer" type="pinteger" />
                        </attribute>
                        <attribute name="readOnly" value="false">
                            <domain name="Boolean" type="boolean" />
                        </attribute>
                    </attributes>
                    <axioms />
                    <subclasses />
                </class>
                <class name="button">
                    <domain type="" />
                    <attributes>
                        <attribute name="name">
                            <domain name="Text" type="text" />
                        </attribute>
                        <attribute name="disabled">
                            <domain name="Boolean" type="boolean" />
                        </attribute>
                    </attributes>
                    <axioms />
                    <subclasses />
                </class>
                <class name="submit">
                    <domain type="" />
                    <attributes>
                        <attribute name="name">
                            <domain name="Text" type="text" />
                        </attribute>
                        <attribute name="disabled">
                            <domain name="Boolean" type="boolean" />
                        </attribute>
                        <attribute name="type" value="submit">
                            <domain type="" />
                        </attribute>
                    </attributes>
                    <axioms />
                    <subclasses />
                </class>
                <class name="reset">
                    <domain type="" />
                    <attributes>
                        <attribute name="name">
                            <domain name="Text" type="text" />
                        </attribute>
                        <attribute name="disabled">
                            <domain name="Boolean" type="boolean" />
                        </attribute>
                        <attribute name="type" value="reset">
                            <domain type="" />
                        </attribute>
                    </attributes>
                    <axioms />
                    <subclasses />
                </class>
                <class name="image">
                    <domain type="" />
                    <attributes>
                        <attribute name="name">
                            <domain name="Text" type="text" />
                        </attribute>
                        <attribute name="disabled">
                            <domain name="Boolean" type="boolean" />
                        </attribute>
                        <attribute name="type" value="image">
                            <domain type="" />
                        </attribute>
                        <attribute name="src">
                            <domain name="URL" type="url" />
                        </attribute>
                    </attributes>
                    <axioms />
                    <subclasses />
                </class>
            </subclasses>
        </class>
    </classes>
    <terms>
        <term name="http://www.jobfinders.freeserve.co.uk/form2.htm" class="page">
            <domain type="" />
            <attributes />
            <axioms />
            <relationships>
                <relationship name="is parent of">
                    <source>http://www.jobfinders.freeserve.co.uk/form2.htm</source>
                    <targets>FrontPage_Form1</targets>
                </relationship>
            </relationships>
            <subterms>
                <term name="FrontPage_Form1" class="form">
                    <domain type="" />
                    <attributes>
                        <attribute name="method" value="POST">
                            <domain name="Choice" type="choice">
                                <entry>post</entry>
                                <entry>get</entry>
                            </domain>
                        </attribute>
                        <attribute name="action" value="mailto:cv@jobfinders.freeserve.co.uk?subject=CV Sent form Jobfinders Site-">
                            <domain name="URL" type="url" />
                        </attribute>
                    </attributes>
                    <axioms />
                    <relationships>
                        <relationship name="is child of">
                            <source>FrontPage_Form1</source>
                            <targets>http://www.jobfinders.freeserve.co.uk/form2.htm</targets>
                        </relationship>
                        <relationship name="is parent of">
                            <source>FrontPage_Form1</source>
                            <targets>Info</targets>
                        </relationship>
                        <relationship name="is parent of">
                            <source>FrontPage_Form1</source>
                            <targets>Name</targets>
                        </relationship>
                        <relationship name="is parent of">
                            <source>FrontPage_Form1</source>
                            <targets>Telephone No (home)</targets>
                        </relationship>
                        <relationship name="is parent of">
                            <source>FrontPage_Form1</source>
                            <targets>Telephone No (Mobile)</targets>
                        </relationship>
                        <relationship name="is parent of">
                            <source>FrontPage_Form1</source>
                            <targets>E-mail address</targets>
                        </relationship>
                        <relationship name="is parent of">
                            <source>FrontPage_Form1</source>
                            <targets>Date of Birth</targets>
                        </relationship>
                        <relationship name="is parent of">
                            <source>FrontPage_Form1</source>
                            <targets>Nationality</targets>
                        </relationship>
                        <relationship name="is parent of">
                            <source>FrontPage_Form1</source>
                            <targets>Clean</targets>
                        </relationship>
                        <relationship name="is parent of">
                            <source>FrontPage_Form1</source>
                            <targets />
                        </relationship>
                        <relationship name="is parent of">
                            <source>FrontPage_Form1</source>
                            <targets>References Available Yes</targets>
                        </relationship>
                        <relationship name="is parent of">
                            <source>FrontPage_Form1</source>
                            <targets>This box is ticked to indicate that you have agreed that your CV can be distributed in relation to</targets>
                        </relationship>
                        <relationship name="is parent of">
                            <source>FrontPage_Form1</source>
                            <targets>Send to Jobfinders</targets>
                        </relationship>
                        <relationship name="is parent of">
                            <source>FrontPage_Form1</source>
                            <targets>References Available Yes No</targets>
                        </relationship>
                        <relationship name="is parent of">
                            <source>FrontPage_Form1</source>
                            <targets>Address</targets>
                        </relationship>
                        <relationship name="is parent of">
                            <source>FrontPage_Form1</source>
                            <targets>Professional Profile</targets>
                        </relationship>
                        <relationship name="is parent of">
                            <source>FrontPage_Form1</source>
                            <targets>Any other D etails</targets>
                        </relationship>
                        <relationship name="is parent of">
                            <source>FrontPage_Form1</source>
                            <targets>Education and Qualifications</targets>
                        </relationship>
                        <relationship name="is parent of">
                            <source>FrontPage_Form1</source>
                            <targets>Further Skills</targets>
                        </relationship>
                        <relationship name="is parent of">
                            <source>FrontPage_Form1</source>
                            <targets>Employment History</targets>
                        </relationship>
                        <relationship name="is parent of">
                            <source>FrontPage_Form1</source>
                            <targets>Interests and Activities</targets>
                        </relationship>
                    </relationships>
                    <subterms>
                        <term name="Info" class="hidden">
                            <domain type="" />
                            <attributes>
                                <attribute name="name" value="Info">
                                    <domain name="Text" type="text" />
                                </attribute>
                                <attribute name="disabled" value="false">
                                    <domain name="Boolean" type="boolean" />
                                </attribute>
                                <attribute name="type">
                                    <domain type="" />
                                </attribute>
                                <attribute name="type">
                                    <domain type="" />
                                </attribute>
                            </attributes>
                            <axioms />
                            <relationships>
                                <relationship name="is child of">
                                    <source>Info</source>
                                    <targets>FrontPage_Form1</targets>
                                </relationship>
                            </relationships>
                            <subterms />
                        </term>
                        <term name="Name" value="" class="text">
                            <domain type="" />
                            <attributes>
                                <attribute name="name" value="Name">
                                    <domain name="Text" type="text" />
                                </attribute>
                                <attribute name="disabled" value="false">
                                    <domain name="Boolean" type="boolean" />
                                </attribute>
                                <attribute name="type">
                                    <domain type="" />
                                </attribute>
                                <attribute name="defaultValue" value="">
                                    <domain name="Text" type="text" />
                                </attribute>
                                <attribute name="value">
                                    <domain name="Text" type="text" />
                                </attribute>
                                <attribute name="size" value="44">
                                    <domain name="Positive Integer" type="pinteger" />
                                </attribute>
                                <attribute name="maxLength">
                                    <domain name="Positive Integer" type="pinteger" />
                                </attribute>
                                <attribute name="readOnly" value="false">
                                    <domain name="Boolean" type="boolean" />
                                </attribute>
                            </attributes>
                            <axioms />
                            <relationships>
                                <relationship name="is child of">
                                    <source>Name</source>
                                    <targets>FrontPage_Form1</targets>
                                </relationship>
                            </relationships>
                            <subterms />
                        </term>
                        <term name="Telephone No (home)" value="" class="text">
                            <domain type="" />
                            <attributes>
                                <attribute name="name" value="Telephone_No_Home">
                                    <domain name="Text" type="text" />
                                </attribute>
                                <attribute name="disabled" value="false">
                                    <domain name="Boolean" type="boolean" />
                                </attribute>
                                <attribute name="type">
                                    <domain type="" />
                                </attribute>
                                <attribute name="defaultValue" value="">
                                    <domain name="Text" type="text" />
                                </attribute>
                                <attribute name="value">
                                    <domain name="Text" type="text" />
                                </attribute>
                                <attribute name="size" value="44">
                                    <domain name="Positive Integer" type="pinteger" />
                                </attribute>
                                <attribute name="maxLength">
                                    <domain name="Positive Integer" type="pinteger" />
                                </attribute>
                                <attribute name="readOnly" value="false">
                                    <domain name="Boolean" type="boolean" />
                                </attribute>
                            </attributes>
                            <axioms />
                            <relationships>
                                <relationship name="is child of">
                                    <source>Telephone No (home)</source>
                                    <targets>FrontPage_Form1</targets>
                                </relationship>
                            </relationships>
                            <subterms />
                        </term>
                        <term name="Telephone No (Mobile)" value="" class="text">
                            <domain type="" />
                            <attributes>
                                <attribute name="name" value="Telephone_No_Mobile">
                                    <domain name="Text" type="text" />
                                </attribute>
                                <attribute name="disabled" value="false">
                                    <domain name="Boolean" type="boolean" />
                                </attribute>
                                <attribute name="type">
                                    <domain type="" />
                                </attribute>
                                <attribute name="defaultValue" value="">
                                    <domain name="Text" type="text" />
                                </attribute>
                                <attribute name="value">
                                    <domain name="Text" type="text" />
                                </attribute>
                                <attribute name="size" value="44">
                                    <domain name="Positive Integer" type="pinteger" />
                                </attribute>
                                <attribute name="maxLength">
                                    <domain name="Positive Integer" type="pinteger" />
                                </attribute>
                                <attribute name="readOnly" value="false">
                                    <domain name="Boolean" type="boolean" />
                                </attribute>
                            </attributes>
                            <axioms />
                            <relationships>
                                <relationship name="is child of">
                                    <source>Telephone No (Mobile)</source>
                                    <targets>FrontPage_Form1</targets>
                                </relationship>
                            </relationships>
                            <subterms />
                        </term>
                        <term name="E-mail address" value="" class="text">
                            <domain type="" />
                            <attributes>
                                <attribute name="name" value="E_mail_address">
                                    <domain name="Text" type="text" />
                                </attribute>
                                <attribute name="disabled" value="false">
                                    <domain name="Boolean" type="boolean" />
                                </attribute>
                                <attribute name="type">
                                    <domain type="" />
                                </attribute>
                                <attribute name="defaultValue" value="">
                                    <domain name="Text" type="text" />
                                </attribute>
                                <attribute name="value">
                                    <domain name="Text" type="text" />
                                </attribute>
                                <attribute name="size" value="44">
                                    <domain name="Positive Integer" type="pinteger" />
                                </attribute>
                                <attribute name="maxLength">
                                    <domain name="Positive Integer" type="pinteger" />
                                </attribute>
                                <attribute name="readOnly" value="false">
                                    <domain name="Boolean" type="boolean" />
                                </attribute>
                            </attributes>
                            <axioms />
                            <relationships>
                                <relationship name="is child of">
                                    <source>E-mail address</source>
                                    <targets>FrontPage_Form1</targets>
                                </relationship>
                            </relationships>
                            <subterms />
                        </term>
                        <term name="Date of Birth" value="" class="text">
                            <domain type="" />
                            <attributes>
                                <attribute name="name" value="Date_of_Birth">
                                    <domain name="Text" type="text" />
                                </attribute>
                                <attribute name="disabled" value="false">
                                    <domain name="Boolean" type="boolean" />
                                </attribute>
                                <attribute name="type">
                                    <domain type="" />
                                </attribute>
                                <attribute name="defaultValue" value="">
                                    <domain name="Text" type="text" />
                                </attribute>
                                <attribute name="value">
                                    <domain name="Text" type="text" />
                                </attribute>
                                <attribute name="size" value="20">
                                    <domain name="Positive Integer" type="pinteger" />
                                </attribute>
                                <attribute name="maxLength">
                                    <domain name="Positive Integer" type="pinteger" />
                                </attribute>
                                <attribute name="readOnly" value="false">
                                    <domain name="Boolean" type="boolean" />
                                </attribute>
                            </attributes>
                            <axioms />
                            <relationships>
                                <relationship name="is child of">
                                    <source>Date of Birth</source>
                                    <targets>FrontPage_Form1</targets>
                                </relationship>
                            </relationships>
                            <subterms />
                        </term>
                        <term name="Nationality" value="" class="text">
                            <domain type="" />
                            <attributes>
                                <attribute name="name" value="Nationality">
                                    <domain name="Text" type="text" />
                                </attribute>
                                <attribute name="disabled" value="false">
                                    <domain name="Boolean" type="boolean" />
                                </attribute>
                                <attribute name="type">
                                    <domain type="" />
                                </attribute>
                                <attribute name="defaultValue" value="">
                                    <domain name="Text" type="text" />
                                </attribute>
                                <attribute name="value">
                                    <domain name="Text" type="text" />
                                </attribute>
                                <attribute name="size" value="20">
                                    <domain name="Positive Integer" type="pinteger" />
                                </attribute>
                                <attribute name="maxLength">
                                    <domain name="Positive Integer" type="pinteger" />
                                </attribute>
                                <attribute name="readOnly" value="false">
                                    <domain name="Boolean" type="boolean" />
                                </attribute>
                            </attributes>
                            <axioms />
                            <relationships>
                                <relationship name="is child of">
                                    <source>Nationality</source>
                                    <targets>FrontPage_Form1</targets>
                                </relationship>
                            </relationships>
                            <subterms />
                        </term>
                        <term name="Clean" value="" class="checkbox">
                            <domain name="Choice" type="choice">
                                <entry>
                                    <term name="Clean" value="Yes">
                                        <domain type="" />
                                        <attributes>
                                            <attribute name="checked" value="false">
                                                <domain type="" />
                                            </attribute>
                                            <attribute name="defaultChecked" value="false">
                                                <domain type="" />
                                            </attribute>
                                        </attributes>
                                        <axioms />
                                        <relationships />
                                        <subterms />
                                    </term>
                                </entry>
                            </domain>
                            <attributes>
                                <attribute name="name" value="Driving_Licence_Full">
                                    <domain name="Text" type="text" />
                                </attribute>
                                <attribute name="disabled" value="false">
                                    <domain name="Boolean" type="boolean" />
                                </attribute>
                                <attribute name="type">
                                    <domain type="" />
                                </attribute>
                            </attributes>
                            <axioms />
                            <relationships>
                                <relationship name="is child of">
                                    <source>Clean</source>
                                    <targets>FrontPage_Form1</targets>
                                </relationship>
                            </relationships>
                            <subterms />
                        </term>
                        <term name="" value="" class="checkbox">
                            <domain name="Choice" type="choice">
                                <entry>
                                    <term name="" value="Yes">
                                        <domain type="" />
                                        <attributes>
                                            <attribute name="checked" value="false">
                                                <domain type="" />
                                            </attribute>
                                            <attribute name="defaultChecked" value="false">
                                                <domain type="" />
                                            </attribute>
                                        </attributes>
                                        <axioms />
                                        <relationships />
                                        <subterms />
                                    </term>
                                </entry>
                            </domain>
                            <attributes>
                                <attribute name="name" value="Driving_Licence_Clean">
                                    <domain name="Text" type="text" />
                                </attribute>
                                <attribute name="disabled" value="false">
                                    <domain name="Boolean" type="boolean" />
                                </attribute>
                                <attribute name="type">
                                    <domain type="" />
                                </attribute>
                            </attributes>
                            <axioms />
                            <relationships>
                                <relationship name="is child of">
                                    <source />
                                    <targets>FrontPage_Form1</targets>
                                </relationship>
                            </relationships>
                            <subterms />
                        </term>
                        <term name="References Available Yes" value="Yes" class="checkbox">
                            <domain name="Choice" type="choice">
                                <entry>
                                    <term name="No" value="Yes">
                                        <domain type="" />
                                        <attributes>
                                            <attribute name="checked" value="true">
                                                <domain type="" />
                                            </attribute>
                                            <attribute name="defaultChecked" value="true">
                                                <domain type="" />
                                            </attribute>
                                        </attributes>
                                        <axioms />
                                        <relationships />
                                        <subterms />
                                    </term>
                                </entry>
                                <entry>
                                    <term name="" value="No">
                                        <domain type="" />
                                        <attributes>
                                            <attribute name="checked" value="false">
                                                <domain type="" />
                                            </attribute>
                                            <attribute name="defaultChecked" value="false">
                                                <domain type="" />
                                            </attribute>
                                        </attributes>
                                        <axioms />
                                        <relationships />
                                        <subterms />
                                    </term>
                                </entry>
                            </domain>
                            <attributes>
                                <attribute name="name" value="References_Available">
                                    <domain name="Text" type="text" />
                                </attribute>
                                <attribute name="disabled" value="false">
                                    <domain name="Boolean" type="boolean" />
                                </attribute>
                                <attribute name="type">
                                    <domain type="" />
                                </attribute>
                            </attributes>
                            <axioms />
                            <relationships>
                                <relationship name="is child of">
                                    <source>References Available Yes</source>
                                    <targets>FrontPage_Form1</targets>
                                </relationship>
                            </relationships>
                            <subterms />
                        </term>
                        <term name="This box is ticked to indicate that you have agreed that your CV can be distributed in relation to" value="Yes" class="checkbox">
                            <domain name="Choice" type="choice">
                                <entry>
                                    <term name="This box is ticked to indicate that you have agreed that your CV can be distributed in relation to" value="Yes">
                                        <domain type="" />
                                        <attributes>
                                            <attribute name="checked" value="true">
                                                <domain type="" />
                                            </attribute>
                                            <attribute name="defaultChecked" value="true">
                                                <domain type="" />
                                            </attribute>
                                        </attributes>
                                        <axioms />
                                        <relationships />
                                        <subterms />
                                    </term>
                                </entry>
                            </domain>
                            <attributes>
                                <attribute name="name" value="Data Protection Agreed">
                                    <domain name="Text" type="text" />
                                </attribute>
                                <attribute name="disabled" value="false">
                                    <domain name="Boolean" type="boolean" />
                                </attribute>
                                <attribute name="type">
                                    <domain type="" />
                                </attribute>
                            </attributes>
                            <axioms />
                            <relationships>
                                <relationship name="is child of">
                                    <source>This box is ticked to indicate that you have agreed that your CV can be distributed in relation to</source>
                                    <targets>FrontPage_Form1</targets>
                                </relationship>
                            </relationships>
                            <subterms />
                        </term>
                        <term name="Send to Jobfinders" class="submit">
                            <domain type="" />
                            <attributes>
                                <attribute name="name" value="">
                                    <domain name="Text" type="text" />
                                </attribute>
                                <attribute name="disabled" value="false">
                                    <domain name="Boolean" type="boolean" />
                                </attribute>
                                <attribute name="type">
                                    <domain type="" />
                                </attribute>
                            </attributes>
                            <axioms />
                            <relationships>
                                <relationship name="is child of">
                                    <source>Send to Jobfinders</source>
                                    <targets>FrontPage_Form1</targets>
                                </relationship>
                            </relationships>
                            <subterms />
                        </term>
                        <term name="References Available Yes No" value="Please Select Type of Employment you are interested in" class="select">
                            <domain name="Choice" type="choice">
                                <entry>
                                    <term name="Please Select Type of Employment you are interested in" value="Please Select Type of Employment you are interested in">
                                        <domain type="" />
                                        <attributes>
                                            <attribute name="selected" value="true">
                                                <domain type="" />
                                            </attribute>
                                            <attribute name="defaultSelected" value="true">
                                                <domain type="" />
                                            </attribute>
                                        </attributes>
                                        <axioms />
                                        <relationships />
                                        <subterms />
                                    </term>
                                </entry>
                                <entry>
                                    <term name="Accounting" value="Accounting">
                                        <domain type="" />
                                        <attributes>
                                            <attribute name="selected" value="false">
                                                <domain type="" />
                                            </attribute>
                                            <attribute name="defaultSelected" value="false">
                                                <domain type="" />
                                            </attribute>
                                        </attributes>
                                        <axioms />
                                        <relationships />
                                        <subterms />
                                    </term>
                                </entry>
                                <entry>
                                    <term name="Banking" value="Banking">
                                        <domain type="" />
                                        <attributes>
                                            <attribute name="selected" value="false">
                                                <domain type="" />
                                            </attribute>
                                            <attribute name="defaultSelected" value="false">
                                                <domain type="" />
                                            </attribute>
                                        </attributes>
                                        <axioms />
                                        <relationships />
                                        <subterms />
                                    </term>
                                </entry>
                                <entry>
                                    <term name="Customer Service" value="Customer Service">
                                        <domain type="" />
                                        <attributes>
                                            <attribute name="selected" value="false">
                                                <domain type="" />
                                            </attribute>
                                            <attribute name="defaultSelected" value="false">
                                                <domain type="" />
                                            </attribute>
                                        </attributes>
                                        <axioms />
                                        <relationships />
                                        <subterms />
                                    </term>
                                </entry>
                                <entry>
                                    <term name="Education" value="Education">
                                        <domain type="" />
                                        <attributes>
                                            <attribute name="selected" value="false">
                                                <domain type="" />
                                            </attribute>
                                            <attribute name="defaultSelected" value="false">
                                                <domain type="" />
                                            </attribute>
                                        </attributes>
                                        <axioms />
                                        <relationships />
                                        <subterms />
                                    </term>
                                </entry>
                                <entry>
                                    <term name="Engineering" value="Engineering">
                                        <domain type="" />
                                        <attributes>
                                            <attribute name="selected" value="false">
                                                <domain type="" />
                                            </attribute>
                                            <attribute name="defaultSelected" value="false">
                                                <domain type="" />
                                            </attribute>
                                        </attributes>
                                        <axioms />
                                        <relationships />
                                        <subterms />
                                    </term>
                                </entry>
                                <entry>
                                    <term name="Executive and Management" value="Executive and Management">
                                        <domain type="" />
                                        <attributes>
                                            <attribute name="selected" value="false">
                                                <domain type="" />
                                            </attribute>
                                            <attribute name="defaultSelected" value="false">
                                                <domain type="" />
                                            </attribute>
                                        </attributes>
                                        <axioms />
                                        <relationships />
                                        <subterms />
                                    </term>
                                </entry>
                                <entry>
                                    <term name="Finance" value="Finance">
                                        <domain type="" />
                                        <attributes>
                                            <attribute name="selected" value="false">
                                                <domain type="" />
                                            </attribute>
                                            <attribute name="defaultSelected" value="false">
                                                <domain type="" />
                                            </attribute>
                                        </attributes>
                                        <axioms />
                                        <relationships />
                                        <subterms />
                                    </term>
                                </entry>
                                <entry>
                                    <term name="Financial Management" value="Financial Management">
                                        <domain type="" />
                                        <attributes>
                                            <attribute name="selected" value="false">
                                                <domain type="" />
                                            </attribute>
                                            <attribute name="defaultSelected" value="false">
                                                <domain type="" />
                                            </attribute>
                                        </attributes>
                                        <axioms />
                                        <relationships />
                                        <subterms />
                                    </term>
                                </entry>
                                <entry>
                                    <term name="General Positions" value="General Positions">
                                        <domain type="" />
                                        <attributes>
                                            <attribute name="selected" value="false">
                                                <domain type="" />
                                            </attribute>
                                            <attribute name="defaultSelected" value="false">
                                                <domain type="" />
                                            </attribute>
                                        </attributes>
                                        <axioms />
                                        <relationships />
                                        <subterms />
                                    </term>
                                </entry>
                                <entry>
                                    <term name="Graduates" value="Graduates">
                                        <domain type="" />
                                        <attributes>
                                            <attribute name="selected" value="false">
                                                <domain type="" />
                                            </attribute>
                                            <attribute name="defaultSelected" value="false">
                                                <domain type="" />
                                            </attribute>
                                        </attributes>
                                        <axioms />
                                        <relationships />
                                        <subterms />
                                    </term>
                                </entry>
                                <entry>
                                    <term name="Health" value="Health">
                                        <domain type="" />
                                        <attributes>
                                            <attribute name="selected" value="false">
                                                <domain type="" />
                                            </attribute>
                                            <attribute name="defaultSelected" value="false">
                                                <domain type="" />
                                            </attribute>
                                        </attributes>
                                        <axioms />
                                        <relationships />
                                        <subterms />
                                    </term>
                                </entry>
                                <entry>
                                    <term name="Health and Safety" value="Health and Safety">
                                        <domain type="" />
                                        <attributes>
                                            <attribute name="selected" value="false">
                                                <domain type="" />
                                            </attribute>
                                            <attribute name="defaultSelected" value="false">
                                                <domain type="" />
                                            </attribute>
                                        </attributes>
                                        <axioms />
                                        <relationships />
                                        <subterms />
                                    </term>
                                </entry>
                                <entry>
                                    <term name="Human Resources" value="Human Resources">
                                        <domain type="" />
                                        <attributes>
                                            <attribute name="selected" value="false">
                                                <domain type="" />
                                            </attribute>
                                            <attribute name="defaultSelected" value="false">
                                                <domain type="" />
                                            </attribute>
                                        </attributes>
                                        <axioms />
                                        <relationships />
                                        <subterms />
                                    </term>
                                </entry>
                                <entry>
                                    <term name="Information Management" value="Information Management">
                                        <domain type="" />
                                        <attributes>
                                            <attribute name="selected" value="false">
                                                <domain type="" />
                                            </attribute>
                                            <attribute name="defaultSelected" value="false">
                                                <domain type="" />
                                            </attribute>
                                        </attributes>
                                        <axioms />
                                        <relationships />
                                        <subterms />
                                    </term>
                                </entry>
                                <entry>
                                    <term name="Information Technology" value="Information Technology">
                                        <domain type="" />
                                        <attributes>
                                            <attribute name="selected" value="false">
                                                <domain type="" />
                                            </attribute>
                                            <attribute name="defaultSelected" value="false">
                                                <domain type="" />
                                            </attribute>
                                        </attributes>
                                        <axioms />
                                        <relationships />
                                        <subterms />
                                    </term>
                                </entry>
                                <entry>
                                    <term name="Investment" value="Investment">
                                        <domain type="" />
                                        <attributes>
                                            <attribute name="selected" value="false">
                                                <domain type="" />
                                            </attribute>
                                            <attribute name="defaultSelected" value="false">
                                                <domain type="" />
                                            </attribute>
                                        </attributes>
                                        <axioms />
                                        <relationships />
                                        <subterms />
                                    </term>
                                </entry>
                                <entry>
                                    <term name="Legal" value="Legal">
                                        <domain type="" />
                                        <attributes>
                                            <attribute name="selected" value="false">
                                                <domain type="" />
                                            </attribute>
                                            <attribute name="defaultSelected" value="false">
                                                <domain type="" />
                                            </attribute>
                                        </attributes>
                                        <axioms />
                                        <relationships />
                                        <subterms />
                                    </term>
                                </entry>
                                <entry>
                                    <term name="Logistics" value="Logistics">
                                        <domain type="" />
                                        <attributes>
                                            <attribute name="selected" value="false">
                                                <domain type="" />
                                            </attribute>
                                            <attribute name="defaultSelected" value="false">
                                                <domain type="" />
                                            </attribute>
                                        </attributes>
                                        <axioms />
                                        <relationships />
                                        <subterms />
                                    </term>
                                </entry>
                                <entry>
                                    <term name="Marketing" value="Marketing">
                                        <domain type="" />
                                        <attributes>
                                            <attribute name="selected" value="false">
                                                <domain type="" />
                                            </attribute>
                                            <attribute name="defaultSelected" value="false">
                                                <domain type="" />
                                            </attribute>
                                        </attributes>
                                        <axioms />
                                        <relationships />
                                        <subterms />
                                    </term>
                                </entry>
                                <entry>
                                    <term name="Media" value="Media">
                                        <domain type="" />
                                        <attributes>
                                            <attribute name="selected" value="false">
                                                <domain type="" />
                                            </attribute>
                                            <attribute name="defaultSelected" value="false">
                                                <domain type="" />
                                            </attribute>
                                        </attributes>
                                        <axioms />
                                        <relationships />
                                        <subterms />
                                    </term>
                                </entry>
                                <entry>
                                    <term name="Multi-Lingual Positions" value="Multi-Lingual Positions">
                                        <domain type="" />
                                        <attributes>
                                            <attribute name="selected" value="false">
                                                <domain type="" />
                                            </attribute>
                                            <attribute name="defaultSelected" value="false">
                                                <domain type="" />
                                            </attribute>
                                        </attributes>
                                        <axioms />
                                        <relationships />
                                        <subterms />
                                    </term>
                                </entry>
                                <entry>
                                    <term name="Other Management and Professional" value="Other Management and Professional">
                                        <domain type="" />
                                        <attributes>
                                            <attribute name="selected" value="false">
                                                <domain type="" />
                                            </attribute>
                                            <attribute name="defaultSelected" value="false">
                                                <domain type="" />
                                            </attribute>
                                        </attributes>
                                        <axioms />
                                        <relationships />
                                        <subterms />
                                    </term>
                                </entry>
                                <entry>
                                    <term name="Productions and Operations" value="Productions and Operations">
                                        <domain type="" />
                                        <attributes>
                                            <attribute name="selected" value="false">
                                                <domain type="" />
                                            </attribute>
                                            <attribute name="defaultSelected" value="false">
                                                <domain type="" />
                                            </attribute>
                                        </attributes>
                                        <axioms />
                                        <relationships />
                                        <subterms />
                                    </term>
                                </entry>
                                <entry>
                                    <term name="Public Sector" value="Public Sector">
                                        <domain type="" />
                                        <attributes>
                                            <attribute name="selected" value="false">
                                                <domain type="" />
                                            </attribute>
                                            <attribute name="defaultSelected" value="false">
                                                <domain type="" />
                                            </attribute>
                                        </attributes>
                                        <axioms />
                                        <relationships />
                                        <subterms />
                                    </term>
                                </entry>
                                <entry>
                                    <term name="Purchasing and Procurement" value="Purchasing and Procurement">
                                        <domain type="" />
                                        <attributes>
                                            <attribute name="selected" value="false">
                                                <domain type="" />
                                            </attribute>
                                            <attribute name="defaultSelected" value="false">
                                                <domain type="" />
                                            </attribute>
                                        </attributes>
                                        <axioms />
                                        <relationships />
                                        <subterms />
                                    </term>
                                </entry>
                                <entry>
                                    <term name="Retail" value="Retail">
                                        <domain type="" />
                                        <attributes>
                                            <attribute name="selected" value="false">
                                                <domain type="" />
                                            </attribute>
                                            <attribute name="defaultSelected" value="false">
                                                <domain type="" />
                                            </attribute>
                                        </attributes>
                                        <axioms />
                                        <relationships />
                                        <subterms />
                                    </term>
                                </entry>
                                <entry>
                                    <term name="Sales and Business Development" value="Sales and Business Development">
                                        <domain type="" />
                                        <attributes>
                                            <attribute name="selected" value="false">
                                                <domain type="" />
                                            </attribute>
                                            <attribute name="defaultSelected" value="false">
                                                <domain type="" />
                                            </attribute>
                                        </attributes>
                                        <axioms />
                                        <relationships />
                                        <subterms />
                                    </term>
                                </entry>
                                <entry>
                                    <term name="Scientific" value="Scientific">
                                        <domain type="" />
                                        <attributes>
                                            <attribute name="selected" value="false">
                                                <domain type="" />
                                            </attribute>
                                            <attribute name="defaultSelected" value="false">
                                                <domain type="" />
                                            </attribute>
                                        </attributes>
                                        <axioms />
                                        <relationships />
                                        <subterms />
                                    </term>
                                </entry>
                                <entry>
                                    <term name="Secretarial and Admin" value="Secretarial and Admin">
                                        <domain type="" />
                                        <attributes>
                                            <attribute name="selected" value="false">
                                                <domain type="" />
                                            </attribute>
                                            <attribute name="defaultSelected" value="false">
                                                <domain type="" />
                                            </attribute>
                                        </attributes>
                                        <axioms />
                                        <relationships />
                                        <subterms />
                                    </term>
                                </entry>
                                <entry>
                                    <term name="Supply Chain" value="Supply Chain">
                                        <domain type="" />
                                        <attributes>
                                            <attribute name="selected" value="false">
                                                <domain type="" />
                                            </attribute>
                                            <attribute name="defaultSelected" value="false">
                                                <domain type="" />
                                            </attribute>
                                        </attributes>
                                        <axioms />
                                        <relationships />
                                        <subterms />
                                    </term>
                                </entry>
                                <entry>
                                    <term name="Telecommunications" value="Telecommunications">
                                        <domain type="" />
                                        <attributes>
                                            <attribute name="selected" value="false">
                                                <domain type="" />
                                            </attribute>
                                            <attribute name="defaultSelected" value="false">
                                                <domain type="" />
                                            </attribute>
                                        </attributes>
                                        <axioms />
                                        <relationships />
                                        <subterms />
                                    </term>
                                </entry>
                                <entry>
                                    <term name="Training" value="Training">
                                        <domain type="" />
                                        <attributes>
                                            <attribute name="selected" value="false">
                                                <domain type="" />
                                            </attribute>
                                            <attribute name="defaultSelected" value="false">
                                                <domain type="" />
                                            </attribute>
                                        </attributes>
                                        <axioms />
                                        <relationships />
                                        <subterms />
                                    </term>
                                </entry>
                                <entry>
                                    <term name="Travel and Hospitality" value="Travel and Hospitality">
                                        <domain type="" />
                                        <attributes>
                                            <attribute name="selected" value="false">
                                                <domain type="" />
                                            </attribute>
                                            <attribute name="defaultSelected" value="false">
                                                <domain type="" />
                                            </attribute>
                                        </attributes>
                                        <axioms />
                                        <relationships />
                                        <subterms />
                                    </term>
                                </entry>
                            </domain>
                            <attributes>
                                <attribute name="name" value="Type_of_Employment_Looking_For">
                                    <domain name="Text" type="text" />
                                </attribute>
                                <attribute name="disabled" value="false">
                                    <domain name="Boolean" type="boolean" />
                                </attribute>
                                <attribute name="type">
                                    <domain type="" />
                                </attribute>
                                <attribute name="size">
                                    <domain name="Positive Integer" type="pinteger" />
                                </attribute>
                                <attribute name="multiple">
                                    <domain name="Boolean" type="boolean" />
                                </attribute>
                            </attributes>
                            <axioms />
                            <relationships>
                                <relationship name="is child of">
                                    <source>References Available Yes No</source>
                                    <targets>FrontPage_Form1</targets>
                                </relationship>
                            </relationships>
                            <subterms />
                        </term>
                        <term name="Address" value="" class="textarea">
                            <domain type="" />
                            <attributes>
                                <attribute name="name" value="Address">
                                    <domain name="Text" type="text" />
                                </attribute>
                                <attribute name="disabled" value="false">
                                    <domain name="Boolean" type="boolean" />
                                </attribute>
                                <attribute name="type">
                                    <domain type="" />
                                </attribute>
                                <attribute name="defaultValue" value="">
                                    <domain name="Text" type="text" />
                                </attribute>
                                <attribute name="rows" value="2">
                                    <domain name="Positive Integer" type="pinteger" />
                                </attribute>
                                <attribute name="cols" value="43">
                                    <domain name="Positive Integer" type="pinteger" />
                                </attribute>
                                <attribute name="readOnly" value="false">
                                    <domain name="Boolean" type="boolean" />
                                </attribute>
                            </attributes>
                            <axioms />
                            <relationships>
                                <relationship name="is child of">
                                    <source>Address</source>
                                    <targets>FrontPage_Form1</targets>
                                </relationship>
                            </relationships>
                            <subterms />
                        </term>
                        <term name="Professional Profile" value="" class="textarea">
                            <domain type="" />
                            <attributes>
                                <attribute name="name" value="Professional_Profile">
                                    <domain name="Text" type="text" />
                                </attribute>
                                <attribute name="disabled" value="false">
                                    <domain name="Boolean" type="boolean" />
                                </attribute>
                                <attribute name="type">
                                    <domain type="" />
                                </attribute>
                                <attribute name="defaultValue" value="">
                                    <domain name="Text" type="text" />
                                </attribute>
                                <attribute name="rows" value="7">
                                    <domain name="Positive Integer" type="pinteger" />
                                </attribute>
                                <attribute name="cols" value="67">
                                    <domain name="Positive Integer" type="pinteger" />
                                </attribute>
                                <attribute name="readOnly" value="false">
                                    <domain name="Boolean" type="boolean" />
                                </attribute>
                            </attributes>
                            <axioms />
                            <relationships>
                                <relationship name="is child of">
                                    <source>Professional Profile</source>
                                    <targets>FrontPage_Form1</targets>
                                </relationship>
                            </relationships>
                            <subterms />
                        </term>
                        <term name="Any other D etails" value="" class="textarea">
                            <domain type="" />
                            <attributes>
                                <attribute name="name" value="Any_other_Details">
                                    <domain name="Text" type="text" />
                                </attribute>
                                <attribute name="disabled" value="false">
                                    <domain name="Boolean" type="boolean" />
                                </attribute>
                                <attribute name="type">
                                    <domain type="" />
                                </attribute>
                                <attribute name="defaultValue" value="">
                                    <domain name="Text" type="text" />
                                </attribute>
                                <attribute name="rows" value="5">
                                    <domain name="Positive Integer" type="pinteger" />
                                </attribute>
                                <attribute name="cols" value="67">
                                    <domain name="Positive Integer" type="pinteger" />
                                </attribute>
                                <attribute name="readOnly" value="false">
                                    <domain name="Boolean" type="boolean" />
                                </attribute>
                            </attributes>
                            <axioms />
                            <relationships>
                                <relationship name="is child of">
                                    <source>Any other D etails</source>
                                    <targets>FrontPage_Form1</targets>
                                </relationship>
                            </relationships>
                            <subterms />
                        </term>
                        <term name="Education and Qualifications" value="" class="textarea">
                            <domain type="" />
                            <attributes>
                                <attribute name="name" value="Education_and_Qualifications">
                                    <domain name="Text" type="text" />
                                </attribute>
                                <attribute name="disabled" value="false">
                                    <domain name="Boolean" type="boolean" />
                                </attribute>
                                <attribute name="type">
                                    <domain type="" />
                                </attribute>
                                <attribute name="defaultValue" value="">
                                    <domain name="Text" type="text" />
                                </attribute>
                                <attribute name="rows" value="5">
                                    <domain name="Positive Integer" type="pinteger" />
                                </attribute>
                                <attribute name="cols" value="67">
                                    <domain name="Positive Integer" type="pinteger" />
                                </attribute>
                                <attribute name="readOnly" value="false">
                                    <domain name="Boolean" type="boolean" />
                                </attribute>
                            </attributes>
                            <axioms />
                            <relationships>
                                <relationship name="is child of">
                                    <source>Education and Qualifications</source>
                                    <targets>FrontPage_Form1</targets>
                                </relationship>
                            </relationships>
                            <subterms />
                        </term>
                        <term name="Further Skills" value="" class="textarea">
                            <domain type="" />
                            <attributes>
                                <attribute name="name" value="Further_Skills">
                                    <domain name="Text" type="text" />
                                </attribute>
                                <attribute name="disabled" value="false">
                                    <domain name="Boolean" type="boolean" />
                                </attribute>
                                <attribute name="type">
                                    <domain type="" />
                                </attribute>
                                <attribute name="defaultValue" value="">
                                    <domain name="Text" type="text" />
                                </attribute>
                                <attribute name="rows" value="5">
                                    <domain name="Positive Integer" type="pinteger" />
                                </attribute>
                                <attribute name="cols" value="67">
                                    <domain name="Positive Integer" type="pinteger" />
                                </attribute>
                                <attribute name="readOnly" value="false">
                                    <domain name="Boolean" type="boolean" />
                                </attribute>
                            </attributes>
                            <axioms />
                            <relationships>
                                <relationship name="is child of">
                                    <source>Further Skills</source>
                                    <targets>FrontPage_Form1</targets>
                                </relationship>
                            </relationships>
                            <subterms />
                        </term>
                        <term name="Employment History" value="" class="textarea">
                            <domain type="" />
                            <attributes>
                                <attribute name="name" value="Employment_History">
                                    <domain name="Text" type="text" />
                                </attribute>
                                <attribute name="disabled" value="false">
                                    <domain name="Boolean" type="boolean" />
                                </attribute>
                                <attribute name="type">
                                    <domain type="" />
                                </attribute>
                                <attribute name="defaultValue" value="">
                                    <domain name="Text" type="text" />
                                </attribute>
                                <attribute name="rows" value="7">
                                    <domain name="Positive Integer" type="pinteger" />
                                </attribute>
                                <attribute name="cols" value="67">
                                    <domain name="Positive Integer" type="pinteger" />
                                </attribute>
                                <attribute name="readOnly" value="false">
                                    <domain name="Boolean" type="boolean" />
                                </attribute>
                            </attributes>
                            <axioms />
                            <relationships>
                                <relationship name="is child of">
                                    <source>Employment History</source>
                                    <targets>FrontPage_Form1</targets>
                                </relationship>
                            </relationships>
                            <subterms />
                        </term>
                        <term name="Interests and Activities" value="" class="textarea">
                            <domain type="" />
                            <attributes>
                                <attribute name="name" value="Interests_and_Activities">
                                    <domain name="Text" type="text" />
                                </attribute>
                                <attribute name="disabled" value="false">
                                    <domain name="Boolean" type="boolean" />
                                </attribute>
                                <attribute name="type">
                                    <domain type="" />
                                </attribute>
                                <attribute name="defaultValue" value="">
                                    <domain name="Text" type="text" />
                                </attribute>
                                <attribute name="rows" value="5">
                                    <domain name="Positive Integer" type="pinteger" />
                                </attribute>
                                <attribute name="cols" value="67">
                                    <domain name="Positive Integer" type="pinteger" />
                                </attribute>
                                <attribute name="readOnly" value="false">
                                    <domain name="Boolean" type="boolean" />
                                </attribute>
                            </attributes>
                            <axioms />
                            <relationships>
                                <relationship name="is child of">
                                    <source>Interests and Activities</source>
                                    <targets>FrontPage_Form1</targets>
                                </relationship>
                            </relationships>
                            <subterms />
                        </term>
                    </subterms>
                </term>
            </subterms>
        </term>
    </terms>
</ontology>

