<?xml version="1.0" encoding="UTF-8"?>
<!DOCTYPE ontology SYSTEM "dtds/ontology.dtd">
<ontology name="AviationFlightOrder" title="Flight Order Details" type="full">
    <classes />
    <terms>
        <term name="FlightNum" value="">
            <domain name="Number" type="number" />
            <attributes />
            <axioms />
            <relationships />
            <subterms />
        </term>
        <term name="FlightCost" value="">
            <domain name="Number" type="number" />
            <attributes />
            <axioms />
            <relationships />
            <subterms />
        </term>
        <term name="Discount" value="">
            <domain name="Number" type="number" />
            <attributes />
            <axioms />
            <relationships />
            <subterms />
        </term>
        <term name="OneWay" value="">
            <domain name="Boolean" type="boolean" />
            <attributes />
            <axioms />
            <relationships />
            <subterms />
        </term>
        <term name="FlightDate" value="">
            <domain name="Date" type="date" />
            <attributes />
            <axioms />
            <relationships />
            <subterms />
        </term>
        <term name="FlightTime" value="">
            <domain name="Time" type="time" />
            <attributes />
            <axioms />
            <relationships />
            <subterms />
        </term>
        <term name="PassengerPassportNo" value="">
            <domain name="Number" type="number" />
            <attributes />
            <axioms />
            <relationships />
            <subterms />
        </term>
    </terms>
</ontology>

