<source url="http://pricingcentral.pricegrabber.com/" interurl="http://pricingcentral.pricegrabber.com/home_music.php/ut=4416fb9ddaf65b60/">
  <srcname> PricingCentrial.com </srcname>
  <form>
    <attrgroup>
      <attr name="All Albums, Artists &amp; Songs" ename="album|artist|song">
        <domain format="text_box" />
      </attr>
      <attr name="All Products" ename="all">
        <domain format="text_box" />
      </attr>
      <attr name="Albums" ename="album">
        <domain format="text_box" />
      </attr>
      <attr name="Songs Titles" ename="song">
        <domain format="text_box" />
      </attr>
      <attr name="Artists" ename="artist">
        <domain format="text_box" />
      </attr>
    </attrgroup>
  </form>
</source>